rxai_sdg/__init__.py
rxai_sdg/base/__init__.py
rxai_sdg/mrl/__init__.py
rxai_sdg/mrl/examples.py
rxai_sdg/mrl/prompts.py
rxai_sdg/sft/__init__.py
rxai_sdg/sft/examples.py
rxai_sdg/sft/prompts.py
rxai_sdg/sft/utils.py
rxai_sdg-0.1.33.dist-info/LICENSE
rxai_sdg-0.1.33.dist-info/METADATA
rxai_sdg-0.1.33.dist-info/WHEEL
rxai_sdg-0.1.33.dist-info/RECORD
