Metadata-Version: 2.3
Name: rxai-sdg
Version: 0.1.33
Summary: Reactive AI - Synthetic Datasets Generator
License: Apache-2.0
Keywords: deep-learning,ai,machine-learning
Author: Adam Filipek
Author-email: adamfilipek@rxai.dev
Requires-Python: >=3.10
Classifier: License :: OSI Approved :: Apache Software License
Classifier: Programming Language :: Python :: 3
Classifier: Programming Language :: Python :: 3.10
Classifier: Programming Language :: Python :: 3.11
Classifier: Programming Language :: Python :: 3.12
Classifier: Programming Language :: Python :: 3.13
Requires-Dist: datasets (>=3.5.0,<4.0.0)
Requires-Dist: huggingface-hub (>=0.30.0,<0.31.0)
Requires-Dist: nltk (>=3.9.1,<4.0.0)
Requires-Dist: ollama (>=0.5.1,<0.6.0)
Requires-Dist: openai (>=1.82.1,<2.0.0)
Project-URL: Homepage, https://rxai.dev/rxai-sdg
Project-URL: Repository, https://github.com/RxAI-dev/rxai-sdg
